simplepush-api/__init__.py
simplepush_api/__init__.py
simplepush_api-0.4.dist-info/DESCRIPTION.rst
simplepush_api-0.4.dist-info/METADATA
simplepush_api-0.4.dist-info/RECORD
simplepush_api-0.4.dist-info/WHEEL
simplepush_api-0.4.dist-info/metadata.json
simplepush_api-0.4.dist-info/top_level.txt
