Metadata-Version: 2.0
Name: simplepush-api
Version: 0.4
Summary: A simplepush API
Home-page: https://github.com/luke-spademan/simplepush/
Author: Luke Spademan
Author-email: luke.spademan@gmail.com
License: MIT
Platform: UNKNOWN
